{
  "project_info": {
    "project_number": "425990734731",
    "firebase_url": "https://dairyiconifriends.firebaseio.com",
    "project_id": "dairyiconifriends",
    "storage_bucket": "dairyiconifriends.appspot.com"
  },
  "client": [
    {
      "client_info": {
        "mobilesdk_app_id": "1:425990734731:android:70a23439a7f4a39fdda58e",
        "android_client_info": {
          "package_name": "com.icche.rudf"
        }
      },
      "oauth_client": [
        {
          "client_id": "425990734731-mp1i67anl5oc7d7ss352qbeqo6j04t8r.apps.googleusercontent.com",
          "client_type": 3
        }
      ],
      "api_key": [
        {
          "current_key": "AIzaSyBo6QLuiuQDSfb6Cy7h3KX60dE5HCI-K8s"
        }
      ],
      "services": {
        "appinvite_service": {
          "other_platform_oauth_client": [
            {
              "client_id": "425990734731-mp1i67anl5oc7d7ss352qbeqo6j04t8r.apps.googleusercontent.com",
              "client_type": 3
            }
          ]
        }
      }
    }
  ],
  "configuration_version": "1"
}